patch_issue/__init__.py
patch_issue/patch_issue.py
patch_issue-1.0.0.dist-info/LICENSE
patch_issue-1.0.0.dist-info/METADATA
patch_issue-1.0.0.dist-info/WHEEL
patch_issue-1.0.0.dist-info/top_level.txt
patch_issue-1.0.0.dist-info/RECORD
