Metadata-Version: 2.1
Name: patch-issue
Version: 1.0.0
Summary: Track your patches easily with Jira integration
Home-page: https://github.com/yakobu/patch_issue
Author: yakobu & shefer
Author-email: ronenya4321@gmail.com
License: MIT
Keywords: patch
Platform: UNKNOWN
Classifier: License :: OSI Approved :: MIT License
Classifier: Topic :: Software Development :: Testing
Classifier: Intended Audience :: Developers
Classifier: Programming Language :: Python :: 2
Classifier: Programming Language :: Python :: 2.7
Classifier: Programming Language :: Python :: 3
Classifier: Programming Language :: Python :: 3.5
Classifier: Programming Language :: Python :: 3.6
Classifier: Operating System :: Microsoft :: Windows
Classifier: Operating System :: POSIX
Classifier: Operating System :: Unix
Classifier: Operating System :: MacOS
Requires-Python: >=2.7,!=3.0.*,!=3.1.*,!=3.2.*,!=3.3.*
Requires-Dist: colored
Provides-Extra: dev
Requires-Dist: property-manager ; extra == 'dev'
Requires-Dist: attrdict ; extra == 'dev'
Requires-Dist: mock ; extra == 'dev'
Requires-Dist: flake8 ; extra == 'dev'
Requires-Dist: pytest ; extra == 'dev'
Requires-Dist: pytest-cov ; extra == 'dev'
